codest/__init__.py
codest/main.py
codest/repository.py
codest/sync.py
codest-0.1.1.dist-info/DESCRIPTION.rst
codest-0.1.1.dist-info/METADATA
codest-0.1.1.dist-info/RECORD
codest-0.1.1.dist-info/WHEEL
codest-0.1.1.dist-info/entry_points.txt
codest-0.1.1.dist-info/metadata.json
codest-0.1.1.dist-info/top_level.txt
