Metadata-Version: 2.0
Name: codest
Version: 0.1.1
Summary: Coding at local like you do it on remote
Home-page: https://github.com/psjay/codest
Author: psjay
Author-email: psjay.peng@gmail.com
License: MIT
Platform: UNKNOWN
Classifier: Programming Language :: Python
Classifier: Programming Language :: Python :: 2
Classifier: Programming Language :: Python :: 2.7
Classifier: Operating System :: POSIX
Classifier: License :: OSI Approved :: MIT License
Classifier: Topic :: Software Development
Classifier: Topic :: Utilities
Requires-Dist: watchdog
